requestlogs/__init__.py
requestlogs/base.py
requestlogs/entries.py
requestlogs/logging.py
requestlogs/middleware.py
requestlogs/storages.py
requestlogs/utils.py
requestlogs/views.py
welcome_django_requestlogs-0.0.3.dist-info/LICENSE.md
welcome_django_requestlogs-0.0.3.dist-info/METADATA
welcome_django_requestlogs-0.0.3.dist-info/WHEEL
welcome_django_requestlogs-0.0.3.dist-info/top_level.txt
welcome_django_requestlogs-0.0.3.dist-info/RECORD
