Metadata-Version: 2.1
Name: welcome-django-requestlogs
Version: 0.0.3
Summary: Audit logging for Django and Django Rest Framework
Home-page: https://github.com/pineapplehq/django-requestlogs
Author: Welcome Engineering
Author-email: platform@heywelcome.com
License: UNKNOWN
Keywords: django,log,logging
Platform: UNKNOWN
Requires-Dist: Django (<4.0,>=1.11)
Requires-Dist: djangorestframework (<4.0,>=3.0)
Requires-Dist: setuptools
Provides-Extra: dev
Requires-Dist: pytest ; extra == 'dev'
